excel_mcp/__init__.py
excel_mcp/__main__.py
excel_mcp/calculations.py
excel_mcp/cell_utils.py
excel_mcp/cell_validation.py
excel_mcp/chart.py
excel_mcp/data.py
excel_mcp/exceptions.py
excel_mcp/formatting.py
excel_mcp/pivot.py
excel_mcp/server.py
excel_mcp/sheet.py
excel_mcp/tables.py
excel_mcp/validation.py
excel_mcp/workbook.py
mcpcn_excel_mcp_server-0.1.8.dist-info/METADATA
mcpcn_excel_mcp_server-0.1.8.dist-info/WHEEL
mcpcn_excel_mcp_server-0.1.8.dist-info/entry_points.txt
mcpcn_excel_mcp_server-0.1.8.dist-info/licenses/LICENSE
mcpcn_excel_mcp_server-0.1.8.dist-info/RECORD
